LICENSE
README.md
setup.py
spacetool/__init__.py
spacetool/__version__.py
spacetool/main_tool.py
spacetool.egg-info/PKG-INFO
spacetool.egg-info/SOURCES.txt
spacetool.egg-info/dependency_links.txt
spacetool.egg-info/requires.txt
spacetool.egg-info/top_level.txt