Metadata-Version: 2.1
Name: spacetool
Version: 0.2.1
Summary: space.top的数据管理工具
Home-page: http://space.top/
Author: Leo Ni
Author-email: nij6173@gmail.com
License: MIT
Keywords: data
Platform: UNKNOWN
Classifier: Programming Language :: Python :: 3
Classifier: License :: OSI Approved :: MIT License
Classifier: Operating System :: OS Independent
Requires-Python: >=3.6,<3.11
License-File: LICENSE
